fastapi_prime/__init__.py
fastapi_prime/fastapi_prime.py
fastapi_prime/crud/app/main.py
fastapi_prime/crud/app/api/blog/blog_controller.py
fastapi_prime/crud/app/api/blog/blog_model.py
fastapi_prime/crud/app/api/blog/blog_router.py
fastapi_prime/crud/app/api/blog/blog_schema.py
fastapi_prime/crud/app/api/blog/blog_service.py
fastapi_prime/crud/app/api/example/example_controller.py
fastapi_prime/crud/app/api/example/example_model.py
fastapi_prime/crud/app/api/example/example_router.py
fastapi_prime/crud/app/api/example/example_schema.py
fastapi_prime/crud/app/api/example/example_service.py
fastapi_prime/crud/app/api/user/user_controller.py
fastapi_prime/crud/app/api/user/user_model.py
fastapi_prime/crud/app/api/user/user_router.py
fastapi_prime/crud/app/api/user/user_schema.py
fastapi_prime/crud/app/api/user/user_service.py
fastapi_prime/crud/app/configuration/config.py
fastapi_prime/crud/app/utils/auth.py
fastapi_prime/crud/app/utils/validations.py
fastapi_prime/file_contents/config.py
fastapi_prime/file_contents/main.py
fastapi_prime/file_contents/router.py
fastapi_prime/file_contents/validations.py
fastapi_prime-1.2.0.dist-info/LICENSE
fastapi_prime-1.2.0.dist-info/METADATA
fastapi_prime-1.2.0.dist-info/WHEEL
fastapi_prime-1.2.0.dist-info/entry_points.txt
fastapi_prime-1.2.0.dist-info/top_level.txt
fastapi_prime-1.2.0.dist-info/RECORD
